cparser/__init__.py
cparser/cgrammar.pg
cparser/generator.py
cparser/parser.py
cparser/visitor.py
cparser-0.5.3.dist-info/licenses/LICENSE
cparser-0.5.3.dist-info/WHEEL
cparser-0.5.3.dist-info/METADATA
cparser-0.5.3.dist-info/RECORD
