Metadata-Version: 2.4
Name: cparser
Version: 0.5.3
Summary: C Parser written in pure Python
Keywords: parser,GLR,C
Author-email: "Typhoon HIL, Inc" <office@typhoon-hil.com>
Maintainer-email: "Typhoon HIL, Inc" <office@typhoon-hil.com>
Requires-Python: >=3.8
Classifier: Development Status :: 4 - Beta
Classifier: Intended Audience :: Developers
Classifier: Intended Audience :: Information Technology
Classifier: Intended Audience :: Science/Research
Classifier: Topic :: Software Development :: Interpreters
Classifier: Topic :: Software Development :: Compilers
Classifier: Topic :: Software Development :: Libraries :: Python Modules
Classifier: License :: OSI Approved :: MIT License
Classifier: Operating System :: OS Independent
Classifier: Programming Language :: Python :: 3
Classifier: Programming Language :: Python :: 3.8
Classifier: Programming Language :: Python :: 3.9
Classifier: Programming Language :: Python :: 3.10
Classifier: Programming Language :: Python :: 3.11
Classifier: Programming Language :: Python :: 3.12
Classifier: Programming Language :: Python :: 3.13
License-File: LICENSE
Requires-Dist: parglare==0.18
Requires-Dist: ruff ; extra == "dev"
Requires-Dist: flit ; extra == "dev"
Requires-Dist: ruff ; extra == "test"
Requires-Dist: coverage ; extra == "test"
Requires-Dist: coveralls ; extra == "test"
Requires-Dist: pytest ; extra == "test"
Project-URL: Changelog, https://github.com/typhoon-hil/cparser/blob/master/CHANGELOG.md
Project-URL: Homepage, https://github.com/typhoon-hil/cparser
Project-URL: Repository, https://github.com/typhoon-hil/cparser
Provides-Extra: dev
Provides-Extra: test
